{
  "params": {
    "M": 20,
    "N": 30,
    "w": 0.3,
    "lambda": 0.001,
    "freq_boost_cap": 3000,
    "dep_beta": 0.1,
    "importance_mode": "additive",
    "importance_decay": null,
    "jit_gamma": null,
    "add_phantom_deps": true,
    "total_chars_available": 6782,
    "embedding_model": "text-embedding-3-small"
  },
  "stats": {
    "total_chars_scheduled": 659,
    "days_used": 30,
    "avg_daily_coherence": 0.3367,
    "per_day": [
      {
        "day": 1,
        "n_chars": 20,
        "coherence": 0.4162
      },
      {
        "day": 2,
        "n_chars": 20,
        "coherence": 0.0444
      },
      {
        "day": 3,
        "n_chars": 20,
        "coherence": 0.3647
      },
      {
        "day": 4,
        "n_chars": 20,
        "coherence": 0.305
      },
      {
        "day": 5,
        "n_chars": 20,
        "coherence": 0.2933
      },
      {
        "day": 6,
        "n_chars": 20,
        "coherence": 0.3782
      },
      {
        "day": 7,
        "n_chars": 20,
        "coherence": 0.3739
      },
      {
        "day": 8,
        "n_chars": 20,
        "coherence": 0.4007
      },
      {
        "day": 9,
        "n_chars": 23,
        "coherence": 0.3274
      },
      {
        "day": 10,
        "n_chars": 24,
        "coherence": 0.3596
      },
      {
        "day": 11,
        "n_chars": 20,
        "coherence": 0.3429
      },
      {
        "day": 12,
        "n_chars": 21,
        "coherence": 0.3868
      },
      {
        "day": 13,
        "n_chars": 23,
        "coherence": 0.3114
      },
      {
        "day": 14,
        "n_chars": 23,
        "coherence": 0.3879
      },
      {
        "day": 15,
        "n_chars": 21,
        "coherence": 0.1657
      },
      {
        "day": 16,
        "n_chars": 24,
        "coherence": 0.4329
      },
      {
        "day": 17,
        "n_chars": 26,
        "coherence": 0.3998
      },
      {
        "day": 18,
        "n_chars": 25,
        "coherence": 0.3722
      },
      {
        "day": 19,
        "n_chars": 21,
        "coherence": 0.3918
      },
      {
        "day": 20,
        "n_chars": 25,
        "coherence": 0.3496
      },
      {
        "day": 21,
        "n_chars": 22,
        "coherence": 0.3548
      },
      {
        "day": 22,
        "n_chars": 21,
        "coherence": 0.343
      },
      {
        "day": 23,
        "n_chars": 26,
        "coherence": 0.3945
      },
      {
        "day": 24,
        "n_chars": 20,
        "coherence": 0.3634
      },
      {
        "day": 25,
        "n_chars": 22,
        "coherence": 0.344
      },
      {
        "day": 26,
        "n_chars": 20,
        "coherence": 0.0446
      },
      {
        "day": 27,
        "n_chars": 24,
        "coherence": 0.3955
      },
      {
        "day": 28,
        "n_chars": 22,
        "coherence": 0.3378
      },
      {
        "day": 29,
        "n_chars": 26,
        "coherence": 0.3911
      },
      {
        "day": 30,
        "n_chars": 20,
        "coherence": 0.3271
      }
    ]
  },
  "schedule": {
    "1": [
      "刀",
      "戈",
      "弓",
      "工",
      "殳",
      "斤",
      "角",
      "石",
      "干",
      "木",
      "竹",
      "凡",
      "土",
      "匕",
      "勺",
      "甬",
      "皿",
      "门",
      "文",
      "弋"
    ],
    "2": [
      "攴",
      "糸",
      "冖",
      "隹",
      "冃",
      "勹",
      "日",
      "彡",
      "夂",
      "匚",
      "月",
      "宀",
      "昜",
      "夕",
      "至",
      "旦",
      "雨",
      "目",
      "才",
      "亡"
    ],
    "3": [
      "鸟",
      "牛",
      "鱼",
      "皮",
      "爪",
      "马",
      "羊",
      "豆",
      "虫",
      "龙",
      "贝",
      "口",
      "人",
      "虎",
      "牙",
      "卜",
      "甲",
      "歹",
      "鹿",
      "肉"
    ],
    "4": [
      "二",
      "召",
      "曰",
      "言",
      "自",
      "耳",
      "儿",
      "各",
      "平",
      "白",
      "犬",
      "们",
      "母",
      "气",
      "甘",
      "水",
      "告",
      "女",
      "或",
      "音"
    ],
    "5": [
      "丝",
      "皂",
      "行",
      "巾",
      "舟",
      "手",
      "心",
      "车",
      "页",
      "衣",
      "力",
      "足",
      "网",
      "止",
      "聿",
      "毛",
      "欠",
      "品",
      "舌",
      "员"
    ],
    "6": [
      "也",
      "十",
      "向",
      "又",
      "早",
      "之",
      "正",
      "走",
      "反",
      "舛",
      "下",
      "垂",
      "彳",
      "如",
      "且",
      "由",
      "曾",
      "加",
      "而",
      "亦"
    ],
    "7": [
      "食",
      "丙",
      "辰",
      "乙",
      "壬",
      "己",
      "辛",
      "巳",
      "黄",
      "丁",
      "蜀",
      "火",
      "豕",
      "羽",
      "鬼",
      "金",
      "酉",
      "申",
      "其",
      "亢"
    ],
    "8": [
      "余",
      "有",
      "八",
      "千",
      "多",
      "九",
      "斗",
      "五",
      "元",
      "一",
      "大",
      "每",
      "几",
      "小",
      "单",
      "圭",
      "寸",
      "米",
      "方",
      "长"
    ],
    "9": [
      "册",
      "古",
      "尚",
      "丰",
      "寺",
      "示",
      "禾",
      "玉",
      "真",
      "田",
      "氏",
      "草",
      "本",
      "林",
      "章",
      "集",
      "朱",
      "丹",
      "仓",
      "卉",
      "妻",
      "屮",
      "屯"
    ],
    "10": [
      "地",
      "国",
      "京",
      "阜",
      "邑",
      "山",
      "川",
      "广",
      "巴",
      "氐",
      "固",
      "艮",
      "苔",
      "台",
      "兀",
      "穴",
      "立",
      "廷",
      "延",
      "廴",
      "建",
      "襄",
      "西",
      "里"
    ],
    "11": [
      "敞",
      "者",
      "那",
      "无",
      "这",
      "以",
      "即",
      "乃",
      "不",
      "了",
      "的",
      "在",
      "尔",
      "非",
      "今",
      "是",
      "勿",
      "来",
      "必",
      "乍"
    ],
    "12": [
      "父",
      "子",
      "士",
      "公",
      "首",
      "民",
      "先",
      "王",
      "老",
      "丿",
      "少",
      "官",
      "高",
      "夫",
      "我",
      "可",
      "你",
      "他",
      "从",
      "令",
      "甫"
    ],
    "13": [
      "胡",
      "午",
      "未",
      "戌",
      "客",
      "逆",
      "斥",
      "屰",
      "朔",
      "番",
      "厂",
      "它",
      "冒",
      "革",
      "免",
      "韦",
      "能",
      "齿",
      "连",
      "户",
      "军",
      "尸",
      "要"
    ],
    "14": [
      "重",
      "同",
      "完",
      "合",
      "周",
      "节",
      "束",
      "齐",
      "和",
      "并",
      "区",
      "串",
      "引",
      "丨",
      "两",
      "次",
      "时",
      "兼",
      "佥",
      "比",
      "更",
      "酋",
      "仑"
    ],
    "15": [
      "畐",
      "叚",
      "咼",
      "厄",
      "巠",
      "敝",
      "病",
      "廾",
      "难",
      "害",
      "猒",
      "厌",
      "尤",
      "死",
      "争",
      "育",
      "生",
      "夭",
      "尼",
      "太",
      "求"
    ],
    "16": [
      "共",
      "会",
      "付",
      "丌",
      "畀",
      "交",
      "对",
      "着",
      "当",
      "相",
      "入",
      "中",
      "受",
      "得",
      "舆",
      "兴",
      "舁",
      "与",
      "把",
      "孚",
      "用",
      "为",
      "央",
      "爰"
    ],
    "17": [
      "夹",
      "带",
      "包",
      "票",
      "券",
      "劵",
      "卷",
      "癶",
      "发",
      "臾",
      "罗",
      "布",
      "支",
      "栾",
      "弯",
      "䜌",
      "随",
      "坐",
      "兑",
      "委",
      "矢",
      "弗",
      "买",
      "夬",
      "囱",
      "曲"
    ],
    "18": [
      "幸",
      "安",
      "危",
      "乎",
      "说",
      "然",
      "好",
      "意",
      "炎",
      "矣",
      "义",
      "阿",
      "血",
      "若",
      "俞",
      "艺",
      "埶",
      "势",
      "知",
      "敢",
      "化",
      "朽",
      "巧",
      "丂",
      "考"
    ],
    "19": [
      "过",
      "出",
      "既",
      "就",
      "登",
      "进",
      "此",
      "前",
      "到",
      "凵",
      "去",
      "复",
      "于",
      "起",
      "作",
      "及",
      "北",
      "开",
      "见",
      "回",
      "因"
    ],
    "20": [
      "鼎",
      "介",
      "术",
      "录",
      "青",
      "易",
      "胥",
      "疏",
      "疋",
      "楚",
      "契",
      "耒",
      "采",
      "斩",
      "丘",
      "夷",
      "刺",
      "鹚",
      "茲",
      "兹",
      "兆",
      "瓜",
      "刃",
      "麻",
      "离"
    ],
    "21": [
      "臣",
      "尹",
      "监",
      "史",
      "东",
      "吾",
      "兄",
      "垚",
      "尧",
      "主",
      "侯",
      "帝",
      "后",
      "弟",
      "朝",
      "曹",
      "朕",
      "司",
      "都",
      "夨",
      "吴",
      "庶"
    ],
    "22": [
      "么",
      "些",
      "只",
      "半",
      "空",
      "片",
      "奇",
      "尾",
      "亚",
      "个",
      "冂",
      "内",
      "柬",
      "扁",
      "身",
      "分",
      "专",
      "爿",
      "皆",
      "邦",
      "旁"
    ],
    "23": [
      "迈",
      "夲",
      "备",
      "具",
      "充",
      "呈",
      "责",
      "禀",
      "㐭",
      "亶",
      "詹",
      "卖",
      "肃",
      "享",
      "祭",
      "畏",
      "答",
      "参",
      "朋",
      "斯",
      "荐",
      "廌",
      "法",
      "占",
      "取",
      "予"
    ],
    "24": [
      "则",
      "系",
      "经",
      "理",
      "度",
      "道",
      "种",
      "式",
      "般",
      "样",
      "学",
      "风",
      "爻",
      "路",
      "步",
      "上",
      "列",
      "第",
      "所",
      "面"
    ],
    "25": [
      "府",
      "乡",
      "屋",
      "禺",
      "市",
      "部",
      "畿",
      "幾",
      "机",
      "宫",
      "亥",
      "六",
      "旬",
      "丑",
      "年",
      "虚",
      "谷",
      "鬲",
      "天",
      "堇",
      "昔",
      "娄"
    ],
    "26": [
      "辡",
      "雚",
      "戔",
      "冘",
      "尞",
      "咅",
      "悤",
      "冓",
      "丩",
      "丣",
      "睪",
      "希",
      "鼓",
      "象",
      "冈",
      "瓦",
      "缶",
      "卑",
      "想",
      "巨"
    ],
    "27": [
      "夐",
      "奂",
      "嘉",
      "壴",
      "彭",
      "彦",
      "秀",
      "利",
      "昌",
      "良",
      "喜",
      "吉",
      "直",
      "乐",
      "端",
      "惪",
      "德",
      "卓",
      "贵",
      "皇",
      "旨",
      "乔",
      "曼",
      "岂"
    ],
    "28": [
      "赤",
      "景",
      "光",
      "冥",
      "焦",
      "没",
      "明",
      "玄",
      "黑",
      "云",
      "深",
      "冰",
      "全",
      "卢",
      "坚",
      "现",
      "果",
      "葬",
      "茻",
      "莫",
      "攸",
      "咸"
    ],
    "29": [
      "疑",
      "留",
      "需",
      "失",
      "折",
      "间",
      "阑",
      "杀",
      "看",
      "关",
      "动",
      "办",
      "执",
      "事",
      "定",
      "解",
      "匃",
      "曷",
      "骨",
      "冎",
      "别",
      "辟",
      "缳",
      "环",
      "瞏",
      "还"
    ],
    "30": [
      "孝",
      "家",
      "童",
      "代",
      "但",
      "保",
      "任",
      "农",
      "袁",
      "卒",
      "她",
      "宗",
      "寿",
      "世",
      "昆",
      "奴",
      "名",
      "肖",
      "某",
      "君"
    ]
  }
}