{
  "senses": [
    {
      "index": 0,
      "part_of_speech": "verb",
      "meaning": "哀怜，怜悯，表示对他人的不幸或苦难感到同情。",
      "examples": [
        "怜悯",
        "可怜",
        "同病相怜"
      ],
      "traditional_char": "憐"
    },
    {
      "index": 1,
      "part_of_speech": "verb",
      "meaning": "爱惜，珍爱，尤其指对美好的事物或人物的爱惜关爱之情。",
      "examples": [
        "怜才",
        "怜爱",
        "顾影自怜",
        "怜香惜玉"
      ],
      "traditional_char": "憐"
    }
  ],
  "formations": [
    {
      "formation_type": "phono_semantic_compound",
      "original_sense_index": 0,
      "note": "形声字，从心，粦声。本义为哀怜、怜悯，表感情。"
    }
  ],
  "edges": [
    {
      "source_index": 0,
      "target_index": 1,
      "evolution_type": "semantic_extension",
      "note": "由表示同情、怜悯扩展为爱惜、关爱的意思，历代文献均有体现。"
    }
  ]
}