{
  "senses": [
    {
      "index": 0,
      "part_of_speech": "noun",
      "meaning": "落叶乔木，叶卵形，花有短梗，实扁圆，木材坚实，可制器具或供建筑用",
      "examples": [
        "榆，白枌。——《说文》",
        "山有樞，隰有榆。——《詩·唐風·山有樞》",
        "我决起而飞抢榆枋。——《庄子·逍遥游》"
      ],
      "traditional_char": "榆"
    },
    {
      "index": 1,
      "part_of_speech": "noun",
      "meaning": "以榆树命名的边塞地带",
      "examples": [
        "累石為城，樹榆為塞。——《汉书·韩安国传》",
        "桑榆暮景"
      ],
      "traditional_char": "榆"
    },
    {
      "index": 2,
      "part_of_speech": "noun",
      "meaning": "星名",
      "examples": [
        "玉衡星散為雞，為鴟……為荊，為榆。——《春秋運斗樞》",
        "天上何所有，歷歷種白榆。——《隴西行》"
      ],
      "traditional_char": "榆"
    },
    {
      "index": 3,
      "part_of_speech": "verb",
      "meaning": "通“輸/瀉”，引流、排泄",
      "examples": [
        "植表施景，榆漏率刻。——《太玄·瑩》"
      ],
      "traditional_char": "榆"
    },
    {
      "index": 4,
      "part_of_speech": "verb",
      "meaning": "通“緛”，縮短",
      "examples": [
        "十二始寒，盡刑；十二小榆，賜予。——《管子·幼官》"
      ],
      "traditional_char": "榆"
    },
    {
      "index": 5,
      "part_of_speech": "verb",
      "meaning": "通“搖”，搖動",
      "examples": [
        "失枕在肩上橫骨間，折使榆臂齊肘，正灸脊中。——《素問·骨空論》"
      ],
      "traditional_char": "榆"
    },
    {
      "index": 6,
      "part_of_speech": "verb",
      "meaning": "通“渝”，变化",
      "examples": [
        "煮棘將榆，齊兵有進，子來救寡人可也。——馬王堆帛書《戰國縱橫家書》"
      ],
      "traditional_char": "榆"
    },
    {
      "index": 7,
      "part_of_speech": "noun",
      "meaning": "姓氏",
      "examples": [],
      "traditional_char": "榆"
    }
  ],
  "formations": [
    {
      "formation_type": "phono_semantic_compound",
      "original_sense_index": 0,
      "note": "从木，俞声。形旁表木类植物，声旁表读音，最初指榆树。"
    }
  ],
  "edges": [
    {
      "source_index": 0,
      "target_index": 1,
      "evolution_type": "metonymy",
      "note": "以榆树为代表的边塞地区，以树代地。"
    },
    {
      "source_index": 0,
      "target_index": 2,
      "evolution_type": "metaphor",
      "note": "植物名转借为星名，常见古汉语借义。"
    },
    {
      "source_index": 0,
      "target_index": 7,
      "evolution_type": "conversion",
      "note": "以榆树为姓，常见以植物名为氏。"
    },
    {
      "source_index": 0,
      "target_index": 3,
      "evolution_type": "phonetical_loan_shift",
      "note": "同音假借用作“揄/輸”，表示瀉出，写作榆，假借用法。"
    },
    {
      "source_index": 0,
      "target_index": 4,
      "evolution_type": "phonetical_loan_shift",
      "note": "同音假借义，表示縮短。"
    },
    {
      "source_index": 0,
      "target_index": 5,
      "evolution_type": "phonetical_loan_shift",
      "note": "同音假借义，表示搖动。"
    },
    {
      "source_index": 0,
      "target_index": 6,
      "evolution_type": "phonetical_loan_shift",
      "note": "同音假借为“渝”，表示变化。"
    }
  ]
}