{
  "senses": [
    {
      "index": 0,
      "part_of_speech": "noun",
      "meaning": "传说中的巨大鸟，大鹏。",
      "examples": [
        "北冥有鱼，其名为鲲。鲲之大，不知其几千里也，化而为鸟，其名为鹏。",
        "鹏之徙于南冥也，水击三千里，抟扶摇而上者九万里。"
      ],
      "traditional_char": "鵬"
    },
    {
      "index": 1,
      "part_of_speech": "noun",
      "meaning": "比喻前程远大或志向宏伟。",
      "examples": [
        "鹏程万里。",
        "鹏图仍矫翼，熊轼且移轮。"
      ],
      "traditional_char": "鵬"
    },
    {
      "index": 2,
      "part_of_speech": "noun",
      "meaning": "气势雄伟、伟大（多用于比喻气势、力量等）。",
      "examples": [
        "鹏力（喻大力）",
        "鹏起（比喻气势雄伟）"
      ],
      "traditional_char": "鵬"
    },
    {
      "index": 3,
      "part_of_speech": "noun",
      "meaning": "奋发有为（借指人奋发直上、有作为）。",
      "examples": [
        "鹏举（比喻奋发直上）",
        "鹏博（比喻奋发有为）"
      ],
      "traditional_char": "鵬"
    },
    {
      "index": 4,
      "part_of_speech": "noun",
      "meaning": "“鹏”的简化字。",
      "examples": [],
      "traditional_char": "鹏"
    }
  ],
  "formations": [
    {
      "formation_type": "phono_semantic_compound",
      "original_sense_index": 0,
      "note": "鵬为形声字，从鸟，朋声，表示巨大的神鸟。"
    },
    {
      "formation_type": "simple_indicative",
      "original_sense_index": 4,
      "note": "“鹏”为“鵬”的简化字，用“月”代替“鳥”保持朋声，表音兼略形。"
    }
  ],
  "edges": [
    {
      "source_index": 0,
      "target_index": 1,
      "evolution_type": "metaphor",
      "note": "以大鹏鸟飞行之远，引申为前程远大等抽象意义；汉魏以来常见。"
    },
    {
      "source_index": 0,
      "target_index": 2,
      "evolution_type": "metaphor",
      "note": "由鹏的巨大力量，比喻伟大、雄伟，多见于文学文本。"
    },
    {
      "source_index": 0,
      "target_index": 3,
      "evolution_type": "metaphor",
      "note": "由鹏奋发高飞，比喻人奋发作为，唐宋诗文常见。"
    },
    {
      "source_index": 0,
      "target_index": 4,
      "evolution_type": "analogy",
      "note": "简化字“鹏”本义等同于“鵬”，20世纪中叶简化"
    }
  ]
}