{
  "senses": [
    {
      "index": 0,
      "part_of_speech": "noun",
      "meaning": "形如屋宇的大帐幕，多用于军用帐幕或宫廷帷帐。",
      "examples": [
        "幄，幕也。——《小尔雅·广服》",
        "子产以幄幕九张行。——《左传·昭公十三年》",
        "运筹帷幄之中，决胜千里之外。——《汉书·高帝纪下》"
      ],
      "traditional_char": "幄"
    },
    {
      "index": 1,
      "part_of_speech": "noun",
      "meaning": "帷帐，帐子，用以遮蔽寝卧、座位等。",
      "examples": [
        "以望中仙人，忽同衾幄，遂疑广寒宫殿，未必在云霄矣。——蒲松龄《聊斋志异·娇娜》",
        "幄坐（垂帐的帝、后座位）"
      ],
      "traditional_char": "幄"
    }
  ],
  "formations": [
    {
      "formation_type": "phono_semantic_compound",
      "original_sense_index": 0,
      "note": "形声字，从巾（帷幕相关），‘屋’为声符。本义为形如屋的大帐幕。"
    }
  ],
  "edges": [
    {
      "source_index": 0,
      "target_index": 1,
      "evolution_type": "semantic_extension",
      "note": "由军用大帐幕引申泛指各种帷帐、帐子的用法，见中古及后世文献。"
    }
  ]
}