{
  "senses": [
    {
      "index": 0,
      "part_of_speech": "verb",
      "meaning": "使人警醒以防止犯错，警戒、提醒。",
      "examples": [
        "惩一儆百",
        "以儆效尤",
        "儆省"
      ],
      "traditional_char": "儆"
    },
    {
      "index": 1,
      "part_of_speech": "noun",
      "meaning": "警报，警示（古同“警”）。",
      "examples": [],
      "traditional_char": "儆"
    }
  ],
  "formations": [
    {
      "formation_type": "phono_semantic_compound",
      "original_sense_index": 0,
      "note": "形声字，从人，敬声，表示警戒、提醒之意。"
    }
  ],
  "edges": [
    {
      "source_index": 0,
      "target_index": 1,
      "evolution_type": "semantic_shift",
      "note": "由警戒、警醒扩展为警报的意思，见于古文用法。"
    }
  ]
}