{
  "senses": [
    {
      "index": 0,
      "part_of_speech": "verb",
      "meaning": "抽拔，拉出，拔起。",
      "examples": [
        "擢发难数",
        "擢茅以为之帅"
      ],
      "traditional_char": "擢"
    },
    {
      "index": 1,
      "part_of_speech": "verb",
      "meaning": "提拔，提升（职位、等级等）。",
      "examples": [
        "擢升",
        "擢用",
        "擢第"
      ],
      "traditional_char": "擢"
    }
  ],
  "formations": [
    {
      "formation_type": "phono_semantic_compound",
      "original_sense_index": 0,
      "note": "形声字，从手，翟声，表示用手拔出。"
    }
  ],
  "edges": [
    {
      "source_index": 0,
      "target_index": 1,
      "evolution_type": "metaphor",
      "note": "由拉拔之意引申为从人群中提拔、提升官职，汉代即有用例。"
    }
  ]
}